{
  "generated_at": "2026-05-26 13:33:16",
  "refresh_context": {
    "trigger": "local",
    "trigger_label": "本地刷新",
    "generated_at": "2026-05-26 13:33:16"
  },
  "summary": {
    "total_picks": 27,
    "unique_symbols": 25,
    "profitable_picks": 20,
    "win_rate": 0.740741,
    "average_return": 0.095189,
    "average_return_5d": 0.175293,
    "average_return_10d": 0.409548,
    "average_return_20d": null
  },
  "records": [
    {
      "id": "20260526-000988-1",
      "symbol": "000988",
      "query_symbol": "000988.SZ",
      "name": "华工科技",
      "note": "推荐价171",
      "recommend_date": "2026-05-26",
      "entry_date": "2026-05-26",
      "entry_price": 171.1,
      "current_price": 171.1,
      "return_rate": 0.0,
      "return_5d": null,
      "return_5d_price": null,
      "return_10d": null,
      "return_10d_price": null,
      "return_20d": null,
      "return_20d_price": null,
      "max_gain": 0.027469,
      "max_gain_price": 175.8,
      "max_drawdown": 0.0,
      "max_drawdown_price": 171.1,
      "is_profitable": false,
      "current_date": "2026-05-26",
      "recommendation_sequence": 1,
      "recommendation_count_for_symbol": 1
    },
    {
      "id": "20260525-00148-1",
      "symbol": "00148",
      "query_symbol": "00148.HK",
      "name": "建滔集团",
      "note": "首次推荐",
      "recommend_date": "2026-05-25",
      "entry_date": "2026-05-26",
      "entry_price": 61.0,
      "current_price": 61.0,
      "return_rate": 0.0,
      "return_5d": null,
      "return_5d_price": null,
      "return_10d": null,
      "return_10d_price": null,
      "return_20d": null,
      "return_20d_price": null,
      "max_gain": 0.013934,
      "max_gain_price": 61.85,
      "max_drawdown": 0.0,
      "max_drawdown_price": 61.0,
      "is_profitable": false,
      "current_date": "2026-05-26",
      "recommendation_sequence": 1,
      "recommendation_count_for_symbol": 1
    },
    {
      "id": "20260525-002364-1",
      "symbol": "002364",
      "query_symbol": "002364.SZ",
      "name": "中恒电气",
      "note": "首次推荐",
      "recommend_date": "2026-05-25",
      "entry_date": "2026-05-25",
      "entry_price": 56.25,
      "current_price": 54.56,
      "return_rate": -0.030044,
      "return_5d": null,
      "return_5d_price": null,
      "return_10d": null,
      "return_10d_price": null,
      "return_20d": null,
      "return_20d_price": null,
      "max_gain": 0.018667,
      "max_gain_price": 57.3,
      "max_drawdown": -0.030044,
      "max_drawdown_price": 54.56,
      "is_profitable": false,
      "current_date": "2026-05-26",
      "recommendation_sequence": 1,
      "recommendation_count_for_symbol": 1
    },
    {
      "id": "20260525-002436-1",
      "symbol": "002436",
      "query_symbol": "002436.SZ",
      "name": "兴森科技",
      "note": "首次推荐",
      "recommend_date": "2026-05-25",
      "entry_date": "2026-05-25",
      "entry_price": 38.12,
      "current_price": 38.74,
      "return_rate": 0.016264,
      "return_5d": null,
      "return_5d_price": null,
      "return_10d": null,
      "return_10d_price": null,
      "return_20d": null,
      "return_20d_price": null,
      "max_gain": 0.036201,
      "max_gain_price": 39.5,
      "max_drawdown": 0.0,
      "max_drawdown_price": 38.12,
      "is_profitable": true,
      "current_date": "2026-05-26",
      "recommendation_sequence": 1,
      "recommendation_count_for_symbol": 1
    },
    {
      "id": "20260525-002886-1",
      "symbol": "002886",
      "query_symbol": "002886.SZ",
      "name": "沃特股份",
      "note": "首次推荐",
      "recommend_date": "2026-05-25",
      "entry_date": "2026-05-25",
      "entry_price": 28.72,
      "current_price": 31.59,
      "return_rate": 0.09993,
      "return_5d": null,
      "return_5d_price": null,
      "return_10d": null,
      "return_10d_price": null,
      "return_20d": null,
      "return_20d_price": null,
      "max_gain": 0.09993,
      "max_gain_price": 31.59,
      "max_drawdown": 0.0,
      "max_drawdown_price": 28.72,
      "is_profitable": true,
      "current_date": "2026-05-26",
      "recommendation_sequence": 1,
      "recommendation_count_for_symbol": 1
    },
    {
      "id": "20260525-300285-1",
      "symbol": "300285",
      "query_symbol": "300285.SZ",
      "name": "国瓷材料",
      "note": "首次推荐",
      "recommend_date": "2026-05-25",
      "entry_date": "2026-05-25",
      "entry_price": 51.15,
      "current_price": 49.93,
      "return_rate": -0.023851,
      "return_5d": null,
      "return_5d_price": null,
      "return_10d": null,
      "return_10d_price": null,
      "return_20d": null,
      "return_20d_price": null,
      "max_gain": 0.037732,
      "max_gain_price": 53.08,
      "max_drawdown": -0.023851,
      "max_drawdown_price": 49.93,
      "is_profitable": false,
      "current_date": "2026-05-26",
      "recommendation_sequence": 1,
      "recommendation_count_for_symbol": 1
    },
    {
      "id": "20260525-301511-1",
      "symbol": "301511",
      "query_symbol": "301511.SZ",
      "name": "德福科技",
      "note": "早盘推荐",
      "recommend_date": "2026-05-25",
      "entry_date": "2026-05-25",
      "entry_price": 108.18,
      "current_price": 107.95,
      "return_rate": -0.002126,
      "return_5d": null,
      "return_5d_price": null,
      "return_10d": null,
      "return_10d_price": null,
      "return_20d": null,
      "return_20d_price": null,
      "max_gain": 0.05195,
      "max_gain_price": 113.8,
      "max_drawdown": -0.002126,
      "max_drawdown_price": 107.95,
      "is_profitable": false,
      "current_date": "2026-05-26",
      "recommendation_sequence": 1,
      "recommendation_count_for_symbol": 1
    },
    {
      "id": "20260525-301526-1",
      "symbol": "301526",
      "query_symbol": "301526.SZ",
      "name": "国际复材",
      "note": "首次推荐",
      "recommend_date": "2026-05-25",
      "entry_date": "2026-05-25",
      "entry_price": 21.56,
      "current_price": 22.7,
      "return_rate": 0.052876,
      "return_5d": null,
      "return_5d_price": null,
      "return_10d": null,
      "return_10d_price": null,
      "return_20d": null,
      "return_20d_price": null,
      "max_gain": 0.070037,
      "max_gain_price": 23.07,
      "max_drawdown": 0.0,
      "max_drawdown_price": 21.56,
      "is_profitable": true,
      "current_date": "2026-05-26",
      "recommendation_sequence": 1,
      "recommendation_count_for_symbol": 1
    },
    {
      "id": "20260525-601208-1",
      "symbol": "601208",
      "query_symbol": "601208.SS",
      "name": "东材科技",
      "note": "首次推荐",
      "recommend_date": "2026-05-25",
      "entry_date": "2026-05-25",
      "entry_price": 53.74,
      "current_price": 53.92,
      "return_rate": 0.003349,
      "return_5d": null,
      "return_5d_price": null,
      "return_10d": null,
      "return_10d_price": null,
      "return_20d": null,
      "return_20d_price": null,
      "max_gain": 0.028098,
      "max_gain_price": 55.25,
      "max_drawdown": 0.0,
      "max_drawdown_price": 53.74,
      "is_profitable": true,
      "current_date": "2026-05-26",
      "recommendation_sequence": 1,
      "recommendation_count_for_symbol": 1
    },
    {
      "id": "20260525-603256-1",
      "symbol": "603256",
      "query_symbol": "603256.SS",
      "name": "宏和科技",
      "note": "首次推荐",
      "recommend_date": "2026-05-25",
      "entry_date": "2026-05-25",
      "entry_price": 175.31,
      "current_price": 185.29,
      "return_rate": 0.056928,
      "return_5d": null,
      "return_5d_price": null,
      "return_10d": null,
      "return_10d_price": null,
      "return_20d": null,
      "return_20d_price": null,
      "max_gain": 0.088757,
      "max_gain_price": 190.87,
      "max_drawdown": 0.0,
      "max_drawdown_price": 175.31,
      "is_profitable": true,
      "current_date": "2026-05-26",
      "recommendation_sequence": 1,
      "recommendation_count_for_symbol": 1
    },
    {
      "id": "20260525-603986-1",
      "symbol": "603986",
      "query_symbol": "603986.SS",
      "name": "兆易创新",
      "note": "二次推荐",
      "recommend_date": "2026-05-24",
      "entry_date": "2026-05-25",
      "entry_price": 514.85,
      "current_price": 508.22,
      "return_rate": -0.012878,
      "return_5d": null,
      "return_5d_price": null,
      "return_10d": null,
      "return_10d_price": null,
      "return_20d": null,
      "return_20d_price": null,
      "max_gain": 0.045003,
      "max_gain_price": 538.02,
      "max_drawdown": -0.012878,
      "max_drawdown_price": 508.22,
      "is_profitable": false,
      "current_date": "2026-05-26",
      "recommendation_sequence": 2,
      "recommendation_count_for_symbol": 2
    },
    {
      "id": "20260523-000636-1",
      "symbol": "000636",
      "query_symbol": "000636.SZ",
      "name": "风华高科",
      "note": "empty",
      "recommend_date": "2026-05-23",
      "entry_date": "2026-05-25",
      "entry_price": 41.38,
      "current_price": 43.03,
      "return_rate": 0.039874,
      "return_5d": null,
      "return_5d_price": null,
      "return_10d": null,
      "return_10d_price": null,
      "return_20d": null,
      "return_20d_price": null,
      "max_gain": 0.051232,
      "max_gain_price": 43.5,
      "max_drawdown": 0.0,
      "max_drawdown_price": 41.38,
      "is_profitable": true,
      "current_date": "2026-05-26",
      "recommendation_sequence": 1,
      "recommendation_count_for_symbol": 1
    },
    {
      "id": "20260523-002463-1",
      "symbol": "002463",
      "query_symbol": "002463.SZ",
      "name": "沪电股份",
      "note": "empty",
      "recommend_date": "2026-05-23",
      "entry_date": "2026-05-25",
      "entry_price": 122.54,
      "current_price": 134.76,
      "return_rate": 0.099723,
      "return_5d": null,
      "return_5d_price": null,
      "return_10d": null,
      "return_10d_price": null,
      "return_20d": null,
      "return_20d_price": null,
      "max_gain": 0.099967,
      "max_gain_price": 134.79,
      "max_drawdown": 0.0,
      "max_drawdown_price": 122.54,
      "is_profitable": true,
      "current_date": "2026-05-26",
      "recommendation_sequence": 1,
      "recommendation_count_for_symbol": 1
    },
    {
      "id": "20260523-300408-1",
      "symbol": "300408",
      "query_symbol": "300408.SZ",
      "name": "三环集团",
      "note": "empty",
      "recommend_date": "2026-05-23",
      "entry_date": "2026-05-25",
      "entry_price": 115.35,
      "current_price": 115.52,
      "return_rate": 0.001474,
      "return_5d": null,
      "return_5d_price": null,
      "return_10d": null,
      "return_10d_price": null,
      "return_20d": null,
      "return_20d_price": null,
      "max_gain": 0.06632,
      "max_gain_price": 123.0,
      "max_drawdown": 0.0,
      "max_drawdown_price": 115.35,
      "is_profitable": true,
      "current_date": "2026-05-26",
      "recommendation_sequence": 1,
      "recommendation_count_for_symbol": 1
    },
    {
      "id": "20260521-002156-1",
      "symbol": "002156",
      "query_symbol": "002156.SZ",
      "name": "通富微电",
      "note": "empty",
      "recommend_date": "2026-05-21",
      "entry_date": "2026-05-21",
      "entry_price": 61.76,
      "current_price": 71.03,
      "return_rate": 0.150097,
      "return_5d": null,
      "return_5d_price": null,
      "return_10d": null,
      "return_10d_price": null,
      "return_20d": null,
      "return_20d_price": null,
      "max_gain": 0.213569,
      "max_gain_price": 74.95,
      "max_drawdown": 0.0,
      "max_drawdown_price": 61.76,
      "is_profitable": true,
      "current_date": "2026-05-26",
      "recommendation_sequence": 1,
      "recommendation_count_for_symbol": 1
    },
    {
      "id": "20260521-600584-1",
      "symbol": "600584",
      "query_symbol": "600584.SS",
      "name": "长电科技",
      "note": "empty",
      "recommend_date": "2026-05-21",
      "entry_date": "2026-05-21",
      "entry_price": 66.84,
      "current_price": 83.4,
      "return_rate": 0.247756,
      "return_5d": null,
      "return_5d_price": null,
      "return_10d": null,
      "return_10d_price": null,
      "return_20d": null,
      "return_20d_price": null,
      "max_gain": 0.316577,
      "max_gain_price": 88.0,
      "max_drawdown": 0.0,
      "max_drawdown_price": 66.84,
      "is_profitable": true,
      "current_date": "2026-05-26",
      "recommendation_sequence": 1,
      "recommendation_count_for_symbol": 1
    },
    {
      "id": "20260521-688820-1",
      "symbol": "688820",
      "query_symbol": "688820.SS",
      "name": "盛合晶微",
      "note": "empty",
      "recommend_date": "2026-05-21",
      "entry_date": "2026-05-21",
      "entry_price": 176.8,
      "current_price": 215.01,
      "return_rate": 0.21612,
      "return_5d": null,
      "return_5d_price": null,
      "return_10d": null,
      "return_10d_price": null,
      "return_20d": null,
      "return_20d_price": null,
      "max_gain": 0.316686,
      "max_gain_price": 232.79,
      "max_drawdown": 0.0,
      "max_drawdown_price": 176.8,
      "is_profitable": true,
      "current_date": "2026-05-26",
      "recommendation_sequence": 2,
      "recommendation_count_for_symbol": 2
    },
    {
      "id": "20260520-603119-1",
      "symbol": "603119",
      "query_symbol": "603119.SS",
      "name": "浙江荣泰",
      "note": "empty",
      "recommend_date": "2026-05-20",
      "entry_date": "2026-05-20",
      "entry_price": 76.89,
      "current_price": 81.57,
      "return_rate": 0.060866,
      "return_5d": null,
      "return_5d_price": null,
      "return_10d": null,
      "return_10d_price": null,
      "return_20d": null,
      "return_20d_price": null,
      "max_gain": 0.11718,
      "max_gain_price": 85.9,
      "max_drawdown": -0.020416,
      "max_drawdown_price": 81.57,
      "is_profitable": true,
      "current_date": "2026-05-26",
      "recommendation_sequence": 1,
      "recommendation_count_for_symbol": 1
    },
    {
      "id": "20260520-605376-1",
      "symbol": "605376",
      "query_symbol": "605376.SS",
      "name": "博迁新材",
      "note": "empty",
      "recommend_date": "2026-05-20",
      "entry_date": "2026-05-20",
      "entry_price": 137.45,
      "current_price": 157.36,
      "return_rate": 0.144853,
      "return_5d": null,
      "return_5d_price": null,
      "return_10d": null,
      "return_10d_price": null,
      "return_20d": null,
      "return_20d_price": null,
      "max_gain": 0.226846,
      "max_gain_price": 168.63,
      "max_drawdown": -0.05699,
      "max_drawdown_price": 157.36,
      "is_profitable": true,
      "current_date": "2026-05-26",
      "recommendation_sequence": 1,
      "recommendation_count_for_symbol": 1
    },
    {
      "id": "20260517-002409-1",
      "symbol": "002409",
      "query_symbol": "002409.SZ",
      "name": "雅克科技",
      "note": "empty",
      "recommend_date": "2026-05-17",
      "entry_date": "2026-05-18",
      "entry_price": 114.19,
      "current_price": 122.64,
      "return_rate": 0.073999,
      "return_5d": 0.122252,
      "return_5d_price": 128.15,
      "return_10d": null,
      "return_10d_price": null,
      "return_20d": null,
      "return_20d_price": null,
      "max_gain": 0.122252,
      "max_gain_price": 128.15,
      "max_drawdown": -0.055242,
      "max_drawdown_price": 113.9,
      "is_profitable": true,
      "current_date": "2026-05-26",
      "recommendation_sequence": 1,
      "recommendation_count_for_symbol": 1
    },
    {
      "id": "20260517-603283-1",
      "symbol": "603283",
      "query_symbol": "603283.SS",
      "name": "赛腾股份",
      "note": "empty",
      "recommend_date": "2026-05-17",
      "entry_date": "2026-05-18",
      "entry_price": 64.03,
      "current_price": 66.93,
      "return_rate": 0.045291,
      "return_5d": 0.088396,
      "return_5d_price": 69.69,
      "return_10d": null,
      "return_10d_price": null,
      "return_20d": null,
      "return_20d_price": null,
      "max_gain": 0.135718,
      "max_gain_price": 72.72,
      "max_drawdown": -0.057324,
      "max_drawdown_price": 66.93,
      "is_profitable": true,
      "current_date": "2026-05-26",
      "recommendation_sequence": 1,
      "recommendation_count_for_symbol": 1
    },
    {
      "id": "20260517-603986-1",
      "symbol": "603986",
      "query_symbol": "603986.SS",
      "name": "兆易创新",
      "note": "empty",
      "recommend_date": "2026-05-17",
      "entry_date": "2026-05-18",
      "entry_price": 399.25,
      "current_price": 508.22,
      "return_rate": 0.272937,
      "return_5d": 0.289543,
      "return_5d_price": 514.85,
      "return_10d": null,
      "return_10d_price": null,
      "return_20d": null,
      "return_20d_price": null,
      "max_gain": 0.347577,
      "max_gain_price": 538.02,
      "max_drawdown": -0.029532,
      "max_drawdown_price": 431.15,
      "is_profitable": true,
      "current_date": "2026-05-26",
      "recommendation_sequence": 1,
      "recommendation_count_for_symbol": 2
    },
    {
      "id": "20260517-688820-1",
      "symbol": "688820",
      "query_symbol": "688820.SS",
      "name": "盛合晶微",
      "note": "empty",
      "recommend_date": "2026-05-17",
      "entry_date": "2026-05-18",
      "entry_price": 188.1,
      "current_price": 215.01,
      "return_rate": 0.143062,
      "return_5d": 0.137321,
      "return_5d_price": 213.93,
      "return_10d": null,
      "return_10d_price": null,
      "return_20d": null,
      "return_20d_price": null,
      "max_gain": 0.237586,
      "max_gain_price": 232.79,
      "max_drawdown": -0.065737,
      "max_drawdown_price": 176.8,
      "is_profitable": true,
      "current_date": "2026-05-26",
      "recommendation_sequence": 1,
      "recommendation_count_for_symbol": 2
    },
    {
      "id": "20260513-002119-1",
      "symbol": "002119",
      "query_symbol": "002119.SZ",
      "name": "康强电子",
      "note": "empty",
      "recommend_date": "2026-05-13",
      "entry_date": "2026-05-13",
      "entry_price": 23.49,
      "current_price": 25.03,
      "return_rate": 0.06556,
      "return_5d": 0.024691,
      "return_5d_price": 24.07,
      "return_10d": null,
      "return_10d_price": null,
      "return_20d": null,
      "return_20d_price": null,
      "max_gain": 0.101745,
      "max_gain_price": 25.88,
      "max_drawdown": -0.071487,
      "max_drawdown_price": 22.73,
      "is_profitable": true,
      "current_date": "2026-05-26",
      "recommendation_sequence": 1,
      "recommendation_count_for_symbol": 1
    },
    {
      "id": "20260508-001309-1",
      "symbol": "001309",
      "query_symbol": "001309.SZ",
      "name": "德明利",
      "note": "empty",
      "recommend_date": "2026-05-08",
      "entry_date": "2026-05-08",
      "entry_price": 597.71,
      "current_price": 654.63,
      "return_rate": 0.09523,
      "return_5d": 0.191314,
      "return_5d_price": 712.06,
      "return_10d": 0.127637,
      "return_10d_price": 674.0,
      "return_20d": null,
      "return_20d_price": null,
      "max_gain": 0.271503,
      "max_gain_price": 759.99,
      "max_drawdown": -0.109395,
      "max_drawdown_price": 654.63,
      "is_profitable": true,
      "current_date": "2026-05-26",
      "recommendation_sequence": 1,
      "recommendation_count_for_symbol": 1
    },
    {
      "id": "20260507-002709-1",
      "symbol": "002709",
      "query_symbol": "002709.SZ",
      "name": "天赐材料",
      "note": "empty",
      "recommend_date": "2026-05-07",
      "entry_date": "2026-05-07",
      "entry_price": 62.8,
      "current_price": 52.33,
      "return_rate": -0.16672,
      "return_5d": -0.116083,
      "return_5d_price": 55.51,
      "return_10d": -0.081051,
      "return_10d_price": 57.71,
      "return_20d": null,
      "return_20d_price": null,
      "max_gain": 0.014331,
      "max_gain_price": 63.7,
      "max_drawdown": -0.16672,
      "max_drawdown_price": 52.33,
      "is_profitable": false,
      "current_date": "2026-05-26",
      "recommendation_sequence": 1,
      "recommendation_count_for_symbol": 1
    },
    {
      "id": "20260506-301666-1",
      "symbol": "301666",
      "query_symbol": "301666.SZ",
      "name": "大普微",
      "note": "empty",
      "recommend_date": "2026-05-06",
      "entry_date": "2026-05-06",
      "entry_price": 379.0,
      "current_price": 727.5,
      "return_rate": 0.919525,
      "return_5d": 0.664908,
      "return_5d_price": 631.0,
      "return_10d": 1.182058,
      "return_10d_price": 827.0,
      "return_20d": null,
      "return_20d_price": null,
      "max_gain": 1.424485,
      "max_gain_price": 918.88,
      "max_drawdown": -0.181656,
      "max_drawdown_price": 727.5,
      "is_profitable": true,
      "current_date": "2026-05-26",
      "recommendation_sequence": 1,
      "recommendation_count_for_symbol": 1
    }
  ],
  "stock_summaries": [
    {
      "symbol": "000988",
      "name": "华工科技",
      "recommendation_count": 1,
      "profitable_count": 0,
      "win_rate": 0.0,
      "average_return": 0.0,
      "latest_return": 0.0,
      "first_recommend_date": "2026-05-26",
      "latest_recommend_date": "2026-05-26"
    },
    {
      "symbol": "603256",
      "name": "宏和科技",
      "recommendation_count": 1,
      "profitable_count": 1,
      "win_rate": 1.0,
      "average_return": 0.056928,
      "latest_return": 0.056928,
      "first_recommend_date": "2026-05-25",
      "latest_recommend_date": "2026-05-25"
    },
    {
      "symbol": "601208",
      "name": "东材科技",
      "recommendation_count": 1,
      "profitable_count": 1,
      "win_rate": 1.0,
      "average_return": 0.003349,
      "latest_return": 0.003349,
      "first_recommend_date": "2026-05-25",
      "latest_recommend_date": "2026-05-25"
    },
    {
      "symbol": "301526",
      "name": "国际复材",
      "recommendation_count": 1,
      "profitable_count": 1,
      "win_rate": 1.0,
      "average_return": 0.052876,
      "latest_return": 0.052876,
      "first_recommend_date": "2026-05-25",
      "latest_recommend_date": "2026-05-25"
    },
    {
      "symbol": "301511",
      "name": "德福科技",
      "recommendation_count": 1,
      "profitable_count": 0,
      "win_rate": 0.0,
      "average_return": -0.002126,
      "latest_return": -0.002126,
      "first_recommend_date": "2026-05-25",
      "latest_recommend_date": "2026-05-25"
    },
    {
      "symbol": "300285",
      "name": "国瓷材料",
      "recommendation_count": 1,
      "profitable_count": 0,
      "win_rate": 0.0,
      "average_return": -0.023851,
      "latest_return": -0.023851,
      "first_recommend_date": "2026-05-25",
      "latest_recommend_date": "2026-05-25"
    },
    {
      "symbol": "002886",
      "name": "沃特股份",
      "recommendation_count": 1,
      "profitable_count": 1,
      "win_rate": 1.0,
      "average_return": 0.09993,
      "latest_return": 0.09993,
      "first_recommend_date": "2026-05-25",
      "latest_recommend_date": "2026-05-25"
    },
    {
      "symbol": "002436",
      "name": "兴森科技",
      "recommendation_count": 1,
      "profitable_count": 1,
      "win_rate": 1.0,
      "average_return": 0.016264,
      "latest_return": 0.016264,
      "first_recommend_date": "2026-05-25",
      "latest_recommend_date": "2026-05-25"
    },
    {
      "symbol": "002364",
      "name": "中恒电气",
      "recommendation_count": 1,
      "profitable_count": 0,
      "win_rate": 0.0,
      "average_return": -0.030044,
      "latest_return": -0.030044,
      "first_recommend_date": "2026-05-25",
      "latest_recommend_date": "2026-05-25"
    },
    {
      "symbol": "00148",
      "name": "建滔集团",
      "recommendation_count": 1,
      "profitable_count": 0,
      "win_rate": 0.0,
      "average_return": 0.0,
      "latest_return": 0.0,
      "first_recommend_date": "2026-05-25",
      "latest_recommend_date": "2026-05-25"
    },
    {
      "symbol": "603986",
      "name": "兆易创新",
      "recommendation_count": 2,
      "profitable_count": 1,
      "win_rate": 0.5,
      "average_return": 0.130029,
      "latest_return": -0.012878,
      "first_recommend_date": "2026-05-17",
      "latest_recommend_date": "2026-05-24"
    },
    {
      "symbol": "300408",
      "name": "三环集团",
      "recommendation_count": 1,
      "profitable_count": 1,
      "win_rate": 1.0,
      "average_return": 0.001474,
      "latest_return": 0.001474,
      "first_recommend_date": "2026-05-23",
      "latest_recommend_date": "2026-05-23"
    },
    {
      "symbol": "002463",
      "name": "沪电股份",
      "recommendation_count": 1,
      "profitable_count": 1,
      "win_rate": 1.0,
      "average_return": 0.099723,
      "latest_return": 0.099723,
      "first_recommend_date": "2026-05-23",
      "latest_recommend_date": "2026-05-23"
    },
    {
      "symbol": "000636",
      "name": "风华高科",
      "recommendation_count": 1,
      "profitable_count": 1,
      "win_rate": 1.0,
      "average_return": 0.039874,
      "latest_return": 0.039874,
      "first_recommend_date": "2026-05-23",
      "latest_recommend_date": "2026-05-23"
    },
    {
      "symbol": "688820",
      "name": "盛合晶微",
      "recommendation_count": 2,
      "profitable_count": 2,
      "win_rate": 1.0,
      "average_return": 0.179591,
      "latest_return": 0.21612,
      "first_recommend_date": "2026-05-17",
      "latest_recommend_date": "2026-05-21"
    },
    {
      "symbol": "600584",
      "name": "长电科技",
      "recommendation_count": 1,
      "profitable_count": 1,
      "win_rate": 1.0,
      "average_return": 0.247756,
      "latest_return": 0.247756,
      "first_recommend_date": "2026-05-21",
      "latest_recommend_date": "2026-05-21"
    },
    {
      "symbol": "002156",
      "name": "通富微电",
      "recommendation_count": 1,
      "profitable_count": 1,
      "win_rate": 1.0,
      "average_return": 0.150097,
      "latest_return": 0.150097,
      "first_recommend_date": "2026-05-21",
      "latest_recommend_date": "2026-05-21"
    },
    {
      "symbol": "605376",
      "name": "博迁新材",
      "recommendation_count": 1,
      "profitable_count": 1,
      "win_rate": 1.0,
      "average_return": 0.144853,
      "latest_return": 0.144853,
      "first_recommend_date": "2026-05-20",
      "latest_recommend_date": "2026-05-20"
    },
    {
      "symbol": "603119",
      "name": "浙江荣泰",
      "recommendation_count": 1,
      "profitable_count": 1,
      "win_rate": 1.0,
      "average_return": 0.060866,
      "latest_return": 0.060866,
      "first_recommend_date": "2026-05-20",
      "latest_recommend_date": "2026-05-20"
    },
    {
      "symbol": "603283",
      "name": "赛腾股份",
      "recommendation_count": 1,
      "profitable_count": 1,
      "win_rate": 1.0,
      "average_return": 0.045291,
      "latest_return": 0.045291,
      "first_recommend_date": "2026-05-17",
      "latest_recommend_date": "2026-05-17"
    },
    {
      "symbol": "002409",
      "name": "雅克科技",
      "recommendation_count": 1,
      "profitable_count": 1,
      "win_rate": 1.0,
      "average_return": 0.073999,
      "latest_return": 0.073999,
      "first_recommend_date": "2026-05-17",
      "latest_recommend_date": "2026-05-17"
    },
    {
      "symbol": "002119",
      "name": "康强电子",
      "recommendation_count": 1,
      "profitable_count": 1,
      "win_rate": 1.0,
      "average_return": 0.06556,
      "latest_return": 0.06556,
      "first_recommend_date": "2026-05-13",
      "latest_recommend_date": "2026-05-13"
    },
    {
      "symbol": "001309",
      "name": "德明利",
      "recommendation_count": 1,
      "profitable_count": 1,
      "win_rate": 1.0,
      "average_return": 0.09523,
      "latest_return": 0.09523,
      "first_recommend_date": "2026-05-08",
      "latest_recommend_date": "2026-05-08"
    },
    {
      "symbol": "002709",
      "name": "天赐材料",
      "recommendation_count": 1,
      "profitable_count": 0,
      "win_rate": 0.0,
      "average_return": -0.16672,
      "latest_return": -0.16672,
      "first_recommend_date": "2026-05-07",
      "latest_recommend_date": "2026-05-07"
    },
    {
      "symbol": "301666",
      "name": "大普微",
      "recommendation_count": 1,
      "profitable_count": 1,
      "win_rate": 1.0,
      "average_return": 0.919525,
      "latest_return": 0.919525,
      "first_recommend_date": "2026-05-06",
      "latest_recommend_date": "2026-05-06"
    }
  ],
  "pending_records": [],
  "failures": []
}
